{
  "id": "7.3.1",
  "segments": [
    {
      "template_id": "lesson_cover",
      "content": {
        "image": {
          "src": "https://www.healthtechdigital.com/wp-content/uploads/Artificial-Intelligence-in-renewable-energy-market-Study-shows-important-fields-of-application.-min.jpg"
        },
        "lesson": "Lesson 1",
        "intro": "M7: Data in Sustainable Energy | Chapter 3 | Lesson 1",
        "title": "Data Science Techniques for Energy Analysis"
      },
      "colorscheme": "dark"
    },
    {
      "template_id": "text",
      "colorscheme": "light",
      "content": {
        "text_elements": [
          {
            "template_id": "subtitle",
            "content": {
              "text": "Lesson Overview"
            }
          },
          {
            "template_id": "subtitle_small",
            "content": {
              "text": "Non magnam consectetur ipsum etincidunt dolor porro."
            }
          },
          {
            "template_id": "paragraph_large",
            "content": {
              "text": "Labore numquam voluptatem dolorem eius ipsum amet. Numquam quaerat dolor quaerat non. Ipsum porro quiquia dolorem est ipsum adipisci eius. Est porro modi non modi consectetur adipisci. Non modi quisquam eius. Dolorem amet dolor dolorem non aliquam adipisci quiquia. Quisquam voluptatem etincidunt sed sit modi aliquam. Labore porro velit modi. Quaerat est etincidunt numquam."
            }
          }
        ]
      }
    },
    {
      "template_id": "key_concepts",
      "color_scheme": "dark",
      "content": {
        "title": "Key Concepts",
        "intro": "Lorem ipsum",
        "concepts": [
          {
            "title": "Voluptatem...",
            "body": "Velit etincidunt eius magnam ut quisquam..",
            "source": "-International Development Organization",
            "image": {
              "src": "https://elements-resized.envatousercontent.com/elements-video-cover-images/3254f24d-2426-43ae-b55d-aedc5cd25fea/video_preview/video_preview_0000.jpg?w=1400&cf_fit=cover&q=85&format=auto&s=8801a0bc8becf7ebb4baee10701611ef4b9f3f6939ca660e3a0b90514b7cf8d2",
              "caption": ""
            }
          },
          {
            "title": "Etincidunt...",
            "body": "Neque numquam amet ipsum eius quisquam consectetur..",
            "source": "",
            "image": {
              "src": "https://live.staticflickr.com/1552/26342931015_38814fbfac_b.jpg",
              "caption": ""
            }
          },
          {
            "title": "Ut...",
            "body": "Dolorem dolorem aliquam numquam..",
            "source": "",
            "image": {
              "src": "https://elementum-esg.co.uk/wp-content/uploads/2024/04/energy-sources.png",
              "caption": ""
            }
          },
          {
            "title": "Amet...",
            "body": "Tempora ipsum ut non amet sed..",
            "source": "",
            "image": {
              "src": "https://csis-website-prod.s3.amazonaws.com/s3fs-public/2024-01/AdobeStock_40869586_Crop1.jpg?VersionId=1HVO4O4gG312NydD1v8CElYVGjfLOYtH",
              "caption": ""
            }
          },
          {
            "title": "Quiquia...",
            "body": "Numquam magnam dolor adipisci quiquia numquam sit..",
            "source": "",
            "image": {
              "src": "https://imgs.mongabay.com/wp-content/uploads/sites/20/2025/02/18142934/29572133848_45af12a4bb_k-e1737653671184.jpg",
              "caption": ""
            }
          }
        ]
      },
      "colorscheme": "dark"
    },
    {
      "template_id": "photo_full_height",
      "colorscheme": "dark",
      "content": {
        "image": {
          "src": "https://www.healthtechdigital.com/wp-content/uploads/Artificial-Intelligence-in-renewable-energy-market-Study-shows-important-fields-of-application.-min.jpg"
        }
      }
    },
    {
      "template_id": "text",
      "colorscheme": "dark",
      "content": {
        "text_elements": [
          {
            "template_id": "subtitle",
            "content": {
              "text": "Neque quaerat quiquia sed est"
            }
          },
          {
            "template_id": "paragraph_medium",
            "content": {
              "text": "Tempora magnam modi modi dolore tempora. Eius sit dolorem numquam numquam velit est non. Dolore voluptatem ipsum ipsum velit dolore. Magnam numquam aliquam sit dolor aliquam non. Tempora voluptatem sit non dolorem porro. Dolor dolore dolorem etincidunt. Magnam quiquia quaerat adipisci modi neque. Dolorem quiquia adipisci dolor. Numquam tempora velit velit quisquam ut. Est numquam modi labore etincidunt."
            }
          }
        ]
      }
    },
    {
      "template_id": "key_takeaways",
      "content": {
        "title": "Key Takeaways",
        "intro": "Consectetur tempora ipsum non amet est labore numquam.",
        "takeaways": [
          {
            "image": {
              "src": "https://iea.imgix.net/5860051d-c92e-4fea-8a90-12bf5334dbef/Renewables_2023_shutterstock_1527609272.jpg"
            },
            "title": "Sit...",
            "description": "Dolor magnam dolorem ut. Eius consectetur quisquam quiquia magnam dolor. Consectetur dolor est sed adipisci magnam modi porro. Quiquia ut quisquam ipsum est tempora dolorem numquam. Consectetur ipsum voluptatem consectetur quisquam labore numquam. Dolor est numquam magnam sit magnam. Velit dolorem ut adipisci dolore quaerat etincidunt. Magnam velit est non etincidunt dolor magnam consectetur. Amet numquam neque sit dolorem voluptatem."
          },
          {
            "image": {
              "src": "https://live.staticflickr.com/3775/10838225595_b7d942e452_h.jpg"
            },
            "title": "Ut...",
            "description": "Etincidunt quisquam magnam numquam dolor sed amet sed. Quaerat ut dolorem adipisci dolore. Dolor dolore sit amet non. Consectetur consectetur eius voluptatem neque etincidunt sit quisquam. Tempora neque aliquam dolore aliquam non. Velit adipisci magnam modi etincidunt eius dolore labore. Non tempora modi quiquia non consectetur. Sed dolorem ipsum eius etincidunt labore amet labore. Aliquam dolorem non sit."
          },
          {
            "image": {
              "src": "https://www.undp.org/sites/g/files/zskgke326/files/2022-07/UNDP-Peru-2018_rural_solar_04-Photo%20UNDP%20Peru-Monica%20Sua%CC%81rez%20Galindo.jpg"
            },
            "title": "Neque...",
            "description": "Modi non dolor est. Aliquam ut dolore tempora tempora non magnam. Est neque labore dolor quiquia adipisci ut quaerat. Dolor est quiquia etincidunt neque quisquam non. Velit dolorem velit dolor est numquam quiquia dolor. Consectetur numquam labore porro quiquia etincidunt. Magnam voluptatem etincidunt magnam."
          }
        ]
      },
      "colorscheme": "dark"
    },
    {
      "template_id": "key_resources",
      "content": {
        "title": "Key Resources",
        "resources": [
          {
            "image": {
              "src": "https://www.undp.org/sites/g/files/zskgke326/files/2023-05/1525381088_0.jpg"
            },
            "text": "Dolor...",
            "description": "Magnam amet eius ipsum. Magnam quiquia magnam labore quisquam. Ut modi quiquia sit sed dolor eius. Tempora quisquam est adipisci neque aliquam quiquia. Dolore amet ut ipsum numquam quiquia dolor. Etincidunt etincidunt adipisci sed consectetur dolor modi neque. Sit velit etincidunt aliquam.",
            "href": "https://www.undp.org/publications/undps-energy-strategy"
          },
          {
            "image": {
              "src": "https://www.undp.org/sites/g/files/zskgke326/files/2022-07/UNDP-Peru-2018_rural_solar_04-Photo%20UNDP%20Peru-Monica%20Sua%CC%81rez%20Galindo.jpg"
            },
            "text": "Voluptatem...",
            "description": "Consectetur dolorem est neque aliquam non. Quiquia modi non labore quaerat consectetur tempora. Numquam velit magnam sed eius est adipisci est. Sit dolor velit quaerat aliquam etincidunt numquam eius. Dolor non amet velit modi dolor quiquia quaerat. Eius quiquia dolore aliquam tempora est voluptatem dolore. Amet magnam dolore velit eius. Quaerat quisquam modi neque.",
            "href": "https://www.undp.org/publications/undps-energy-strategy"
          },
          {
            "image": {
              "src": "https://live.staticflickr.com/1552/26342931015_38814fbfac_b.jpg"
            },
            "text": "Dolor...",
            "description": "Modi voluptatem neque ipsum dolore amet dolor. Sit tempora etincidunt ipsum consectetur quisquam modi. Dolor sed tempora porro etincidunt. Voluptatem sed voluptatem quaerat aliquam. Sit porro non sit sed dolore. Magnam aliquam dolorem etincidunt quaerat labore etincidunt. Porro aliquam consectetur eius dolorem modi porro magnam.",
            "href": "https://www.undp.org/publications/undps-energy-strategy"
          }
        ],
        "intro": "Neque non modi est consectetur."
      },
      "colorscheme": "light"
    },
    {
      "template_id": "connection_next",
      "content": {
        "image": {
          "src": "https://iea.imgix.net/5860051d-c92e-4fea-8a90-12bf5334dbef/Renewables_2023_shutterstock_1527609272.jpg",
          "caption": ""
        },
        "intro": "Next up",
        "title": "Energy Modelling Tools and Applications",
        "cta": "Start learning",
        "nextLessonId": "7.3.2"
      }
    }
  ]
}