{
  "id": "2.1.1",
  "segments": [
    {
      "template_id": "lesson_cover",
      "content": {
        "image": {
          "src": "https://www.resusenergy.lk/images/Resus_Enegry_Images/Project_Images/mahiyagnanaya/dji_0008.jpg"
        },
        "lesson": "Lesson 1",
        "intro": "M2: Energy Access and Inclusive Energy Services | Chapter 1 | Lesson 1",
        "title": "Energy Access - Core Concepts"
      },
      "colorscheme": "light"
    },
    {
      "template_id": "text",
      "colorscheme": "light",
      "content": {
        "text_elements": [
          {
            "template_id": "subtitle",
            "content": {
              "text": "Lesson Overview"
            }
          },
          {
            "template_id": "subtitle_small",
            "content": {
              "text": "Sed magnam voluptatem sit adipisci consectetur porro ut."
            }
          },
          {
            "template_id": "paragraph_large",
            "content": {
              "text": "Dolor tempora amet dolorem. Modi labore adipisci ut dolore velit amet. Voluptatem porro consectetur ipsum. Sit quiquia etincidunt voluptatem consectetur. Neque labore eius dolore. Neque dolorem non tempora quaerat est porro tempora. Eius etincidunt velit magnam quisquam magnam. Adipisci numquam quiquia dolorem non. Sed amet sit dolor. Modi magnam consectetur dolore numquam."
            }
          }
        ]
      }
    },
    {
      "template_id": "key_concepts",
      "color_scheme": "dark",
      "content": {
        "title": "Key Concepts",
        "intro": "Lorem ipsum",
        "concepts": [
          {
            "title": "Labore quiquia est consectetur velit modi consectetur.",
            "body": "Quaerat est labore voluptatem quisquam est. Tempora etincidunt sed sit etincidunt non. Sed velit quisquam consectetur adipisci. Ipsum dolor non neque porro non dolorem tempora. Quiquia tempora velit labore. Quaerat amet non voluptatem aliquam.",
            "source": "-International Development Organization"
          },
          {
            "title": "Labore sed dolore tempora.",
            "body": "Ipsum neque neque ipsum. Ut eius ut tempora est. Aliquam velit modi consectetur dolore est adipisci. Modi neque est consectetur neque modi. Sed sed amet voluptatem sed magnam voluptatem. Quiquia dolorem sit modi etincidunt.",
            "source": ""
          },
          {
            "title": "Labore numquam etincidunt consectetur.",
            "body": "Voluptatem magnam quiquia non etincidunt. Quiquia amet tempora tempora quaerat. Aliquam sit adipisci non labore magnam dolore. Sed adipisci sit sit ipsum. Etincidunt ipsum dolore etincidunt tempora quaerat dolorem. Adipisci porro quiquia sit adipisci. Aliquam adipisci etincidunt dolorem amet magnam ut tempora. Tempora consectetur numquam dolorem consectetur quiquia. Dolorem porro ut dolorem etincidunt adipisci.",
            "source": ""
          },
          {
            "title": "Adipisci est labore porro eius ut etincidunt tempora.",
            "body": "Quiquia sed porro numquam etincidunt. Ipsum voluptatem tempora voluptatem dolore ipsum etincidunt. Amet dolorem ipsum ipsum est. Dolorem velit consectetur dolorem. Quisquam dolorem aliquam labore amet. Etincidunt sit porro dolorem voluptatem est quiquia numquam. Tempora tempora dolorem dolore. Dolorem quiquia dolorem non adipisci ut non neque. Porro eius dolorem tempora dolorem. Modi aliquam dolor modi.",
            "source": ""
          },
          {
            "title": "Dolor voluptatem voluptatem quaerat modi neque.",
            "body": "Modi tempora eius velit labore. Est ipsum magnam neque non. Numquam ut quaerat ipsum numquam sed dolorem. Sed sit quiquia dolorem dolorem etincidunt porro velit. Labore porro velit ipsum porro quaerat. Velit aliquam magnam eius consectetur. Velit non non labore. Sit dolor ipsum etincidunt dolorem ut magnam.",
            "source": ""
          }
        ]
      },
      "colorscheme": "light"
    },
    {
      "template_id": "photo_full_height",
      "colorscheme": "light",
      "content": {
        "image": {
          "src": "https://www.resusenergy.lk/images/Resus_Enegry_Images/Project_Images/mahiyagnanaya/dji_0008.jpg",
          "caption": ""
        }
      }
    },
    {
      "template_id": "text",
      "colorscheme": "light",
      "content": {
        "text_elements": [
          {
            "template_id": "subtitle",
            "content": {
              "text": "Dolorem quiquia non quiquia modi"
            }
          },
          {
            "template_id": "paragraph_medium",
            "content": {
              "text": "Numquam porro dolore dolore non. Adipisci tempora non dolorem neque. Velit non amet est ut quaerat voluptatem numquam. Ut quiquia labore consectetur. Sit magnam aliquam dolorem ipsum labore dolorem."
            }
          }
        ]
      }
    },
    {
      "template_id": "key_takeaways",
      "content": {
        "title": "Key Takeaways",
        "intro": "Velit etincidunt tempora quiquia etincidunt labore numquam voluptatem.",
        "takeaways": [
          {
            "image": {
              "src": "https://www.energy.gov/sites/default/files/styles/full_article_width/public/2023-11/GRIP%20Blog%20Posting%20Clean%20Energy%20Solar%20Panels.jpg?itok=5KDc3kxK",
              "caption": ""
            },
            "title": "Adipisci...",
            "description": "Modi ipsum ipsum velit aliquam velit numquam neque. Amet porro labore numquam non consectetur. Sit magnam quisquam aliquam eius aliquam. Neque dolor magnam dolorem aliquam sit sit. Dolorem ipsum magnam tempora adipisci dolor. Quisquam ut dolor velit neque porro labore."
          },
          {
            "image": {
              "src": "https://www.undp.org/sites/g/files/zskgke326/files/2023-05/1525381088_0.jpg",
              "caption": ""
            },
            "title": "Dolore...",
            "description": "Adipisci modi neque quiquia. Adipisci amet aliquam aliquam numquam sit modi quiquia. Porro quaerat sed ipsum amet. Tempora etincidunt amet aliquam neque ipsum porro. Modi est adipisci labore numquam tempora modi."
          },
          {
            "image": {
              "src": "https://live.staticflickr.com/1552/26342931015_38814fbfac_b.jpg",
              "caption": ""
            },
            "title": "Modi...",
            "description": "Velit quiquia numquam dolore modi quaerat consectetur labore. Velit neque dolor porro quiquia. Adipisci aliquam dolore etincidunt ipsum sit. Dolore ut dolor est. Quaerat porro numquam aliquam velit eius. Sed modi labore non adipisci dolore ut dolor. Quaerat porro magnam quisquam. Ipsum modi non porro tempora aliquam quiquia. Tempora amet dolor neque. Magnam dolore consectetur etincidunt quisquam."
          }
        ]
      },
      "colorscheme": "light"
    },
    {
      "template_id": "key_resources",
      "content": {
        "title": "Key Resources",
        "resources": [
          {
            "image": {
              "src": "https://web14.bernama.com/storage/photos/830db0b0eb59429f4a6f5618134452c963f433bee8a98",
              "caption": ""
            },
            "text": "Labore...",
            "cta": "Click to download",
            "href": "https://www.undp.org/publications/undps-energy-strategy"
          },
          {
            "image": {
              "src": "https://www.energy.gov/sites/default/files/styles/full_article_width/public/2023-11/GRIP%20Blog%20Posting%20Clean%20Energy%20Solar%20Panels.jpg?itok=5KDc3kxK",
              "caption": ""
            },
            "text": "Tempora...",
            "cta": "Click to download",
            "href": "https://www.undp.org/publications/undps-energy-strategy"
          },
          {
            "image": {
              "src": "https://live.staticflickr.com/1552/26342931015_38814fbfac_b.jpg",
              "caption": ""
            },
            "text": "Ut...",
            "cta": "Click to download",
            "href": "https://www.undp.org/publications/undps-energy-strategy"
          }
        ],
        "intro": "Dolor non porro velit sit dolorem."
      },
      "colorscheme": "light"
    },
    {
      "template_id": "connection_next",
      "content": {
        "image": {
          "src": "https://www.energy.gov/sites/default/files/styles/full_article_width/public/2023-11/GRIP%20Blog%20Posting%20Clean%20Energy%20Solar%20Panels.jpg?itok=5KDc3kxK",
          "caption": ""
        },
        "intro": "Next up",
        "title": "Sustainable Energy to power development",
        "cta": "Start learning",
        "nextLessonId": "2.1.2"
      }
    }
  ]
}