{
  "id": "3.4.-1",
  "segments": [
    {
      "template_id": "chapter_outro",
      "colorscheme": "dark",
      "content": {
        "intro": "This concludes",
        "title": "tmp",
        "subtitle": "Lorem ipsum dolor sit amet consectetur",
        "body": "tmp",
        "nextBlock": {
          "intro": "Interactive Scenario",
          "title": "Title of the scenario",
          "cta": "You have a meeting with the minister of energy to discuss data-driven policy. Are you ready?",
          "button_cta": "Launch the interactive scenario",
          "image": {
            "src": "https://ik.imagekit.io/seacademy/Photos/Module_5/M5_C3_L1_10.png",
            "caption": "image caption"
          },
          "nextBlockId": "1.1.5"
        }
      }
    },
    {
      "template_id": "connection_next",
      "colorscheme": "dark",
      "content": {
        "image": {
          "src": "https://ik.imagekit.io/seacademy/Photos/Module_5/M5_C2_L3_5.png",
          "caption": ""
        },
        "intro": "Next up",
        "title": "Chapter: Geospatial Data in Electrification planning and policy",
        "nextLessonId": "3.-1.0",
        "cta": "Start learning"
      }
    }
  ]
}